minio/__init__.py
minio/api.py
minio/commonconfig.py
minio/crypto.py
minio/datatypes.py
minio/deleteobjects.py
minio/error.py
minio/helpers.py
minio/legalhold.py
minio/lifecycleconfig.py
minio/minioadmin.py
minio/notificationconfig.py
minio/objectlockconfig.py
minio/py.typed
minio/replicationconfig.py
minio/retention.py
minio/select.py
minio/signer.py
minio/sse.py
minio/sseconfig.py
minio/tagging.py
minio/time.py
minio/versioningconfig.py
minio/xml.py
minio/credentials/__init__.py
minio/credentials/credentials.py
minio/credentials/providers.py
minio-7.2.2.dist-info/LICENSE
minio-7.2.2.dist-info/METADATA
minio-7.2.2.dist-info/NOTICE
minio-7.2.2.dist-info/WHEEL
minio-7.2.2.dist-info/top_level.txt
minio-7.2.2.dist-info/RECORD
