Metadata-Version: 2.1
Name: minio
Version: 7.2.2
Summary: MinIO Python SDK for Amazon S3 Compatible Cloud Storage
Home-page: https://github.com/minio/minio-py
Download-URL: https://github.com/minio/minio-py/releases
Author: MinIO, Inc.
Author-email: dev@min.io
License: Apache-2.0
Classifier: Development Status :: 5 - Production/Stable
Classifier: Intended Audience :: Developers
Classifier: License :: OSI Approved :: Apache Software License
Classifier: Natural Language :: English
Classifier: Operating System :: OS Independent
Classifier: Programming Language :: Python
Classifier: Programming Language :: Python :: 3.7
Classifier: Programming Language :: Python :: 3.8
Classifier: Programming Language :: Python :: 3.9
Classifier: Programming Language :: Python :: 3.10
Classifier: Programming Language :: Python :: 3.11
Classifier: Topic :: Software Development :: Libraries :: Python Modules
License-File: LICENSE
License-File: NOTICE
Requires-Dist: certifi
Requires-Dist: urllib3 (>=2.0)
Requires-Dist: argon2-cffi
Requires-Dist: pycryptodome
Requires-Dist: typing-extensions
